README.txt
setup.py
PACtool.egg-info/PKG-INFO
PACtool.egg-info/SOURCES.txt
PACtool.egg-info/dependency_links.txt
PACtool.egg-info/requires.txt
PACtool.egg-info/top_level.txt
analysis/__init__.py
analysis/analysis_pipeline.py
pactool/LDanalysis.py
pactool/__init__.py
pactool/association_test.py
pactool/frequencies.py
pactool/getinfo.py
pactool/hwe.py
pactool/kor.py
pactool/ld.py
pactool/multitools.py
pactool/pactool.py