Metadata-Version: 1.0
Name: PACtool
Version: 1.1.0
Summary: This is our little project for GWAS
Home-page: https://github.com/pnatsi/PACtool
Author: Akis, Christina, Paschalis
Author-email: pnatsidis@hotmail.com
License: MIT
Keywords: project python linux gwas bioinfo-grad
Platform: UNKNOWN
